{
  "RATE":
  {
    "name": "Rate Only"
  },
  "REWARDS":
  {
    "name": "Rewards"
  },
  "PACKAGE":
  {
    "name": "Package"
  },
  "OPENING":
  {
    "name": "Hotel Opening"
  },
  "BRANDING":
  {
    "name": "Other Brand Package"
  },
  "LOYALTY-OFFER":
  {
    "name": "Loyalty Offers (MI, RC & SW)"
  },
  "PARTNERSHIP":
  {
    "name": "Partnership (Credit Card, Airlines)"
  },
  "MULTIPLE":
  {
    "name": "Multiple Offers"
  },
  "OTHER-PROMOTION":
  {
    "name": "Other Brand Package"
  },
  "NO-PROMOTION":
  {
    "name": "No Offer"
  }
}
